Workbook

Sheet PORTADA
B2: Modelo de ROI — Plan comercial Selmark (versión actualizada)
B4: TFG · Análisis de cliente y geomarketing en moda íntima — Capítulo 8
B6: Versión actualizada y reconciliada con el Capítulo 7 corregido (modelo de churn Random Forest,
B7: enfoque fresh churn, caso de máxima prioridad 16352). Marco DO NOTHING vs DO SOMETHING.
B9: CÓMO USAR EL MODELO:
B10: · Solo se editan las celdas en AZUL de la hoja PARAMETROS.
B11: · Las celdas en NEGRO son fórmulas (se recalculan solas); las VERDES son enlaces entre hojas.
B12: · El resultado final está en la hoja ESCENARIOS; las simulaciones, en SENSIBILIDAD.
B14: HOJAS:
B15: PARAMETROS — todos los inputs editables (universos, tasas, tickets, costes, DO NOTHING).
B16: PALANCAS — ingresos incrementales por palanca (Opción 1 y Opción 2).
B17: ESCENARIOS — DO NOTHING vs Opción 1 vs Opción 2 y ROI final.
... B19: NOTAS — definición de universos y trazabilidad a los capítulos del TFG.

Sheet PARAMETROS
A1: PARÁMETROS EDITABLES (celdas azules)
A3: UNIVERSOS — clientes objetivo de cada palanca
A4: P1 · Retención Núcleo (C1) | B4: 17 | C4: Núcleo en riesgo priorizados — ranking RF corregido (Cap. 7)
A5: P2 · Retención Grandes Cuentas (C2) | B5: 9 | C5: Grandes Cuentas en riesgo priorizadas (Cap. 7)
A6: P3 · Captación Madrid | B6: 127 | C6: Huecos territoriales del Núcleo en Madrid (Cap. 6)
A7: P4 · Conversión C4->C1 Italia | B7: 271 | C7: Compradores Estacionales italianos (Cap. 6)
A9: TASAS DE ÉXITO
A10: P1 · Retención Núcleo | B10: 0.3 | C10: Benchmark Customer Success B2B
A11: P2 · Retención Grandes Cuentas | B11: 0.3 | C11: Benchmark Customer Success B2B
A12: P3 · Captación Madrid | B12: 0.08 | C12: Captación B2B en frío, año 1
A13: P4 · Conversión Italia | B13: 0.04 | C13: Upgrade de cluster (conservador)
A15: TICKETS ANUALES (€)
A16: Ticket C1 (Núcleo) | B16: 16380 | C16: 65.532 € (Cap. 5, Tabla 5.3) / 4 años
A17: Ticket C2 (Grandes Cuentas) | B17: 70640 | C17: 282.555 € (Cap. 5) / 4 años
A18: Ticket captación Madrid (= C1) | B18: 16380 | C18: perfil Núcleo
A19: Diferencial conversión Italia (C1 - C4) | B19: 13672 | C19: 16.380 - 2.708 €
A21: UPLIFT OPCIÓN 2 (reenfoque por cluster, Cap. 5)
A22: Uplift de ticket en P3 y P4 | B22: 0.08 | C22: Reenfoque de oferta hacia clusters de mayor ticket
A24: COSTES FIJOS (€)
A25: Business Analyst (1 FTE) | B25: 55000 | C25: Glassdoor + 40% cargas
A26: Customer Success Manager | B26: 50000
A27: Comercial Madrid | B27: 55000
A28: Agente Italia | B28: 50000
A29: Infraestructura Data + Email + CRM | B29: 12000 | C29: AWS + SaaS marketing
A30: Subtotal costes fijos | B30: =SUM(B25:B29) -> 222000
A32: COSTES VARIABLES (€)
A33: Campañas de marketing (medios) | B33: 100000
A34: Diseño, localización y visitas | B34: 65000
A35: Samples y onboarding | B35: 60000
A36: Generales / administración / legal | B36: 35000
A37: Subtotal costes variables | B37: =SUM(B33:B36) -> 260000
A39: COSTE TOTAL DEL PLAN | B39: =B30+B37 -> 482000
A41: DO NOTHING — facturación 2026 (€)
A42: Forecast retail (Anexo SARIMA) | B42: 15950000 | C42: 15,95 M€ (Anexo A)
A43: B2B inercial (media 2022-2025) | B43: 21300000 | C43: proyección inercial
A44: Total DO NOTHING | B44: =B42+B43 -> 37250000
A46: OTROS
A47: Coste asignado a P1 (ROI individual) | B47: 107000 | C47: CSM dedicado + samples premium

Sheet PALANCAS
A1: INGRESOS INCREMENTALES POR PALANCA
A3: Palanca | B3: Universo | C3: Tasa | D3: Clientes efectivos | E3: Ticket Op.1 | F3: Ingreso Op.1 | G3: Ticket Op.2 | H3: Ingreso Op.2
A4: P1 · Retención Núcleo (C1) | B4: =PARAMETROS!$B$4 -> 17 | C4: =PARAMETROS!$B$10 -> 0.3 | D4: =B4*C4 -> 5.1 | E4: =PARAMETROS!$B$16 -> 16380 | F4: =D4*E4 -> 83538 | G4: =E4 -> 16380 | H4: =D4*G4 -> 83538
A5: P2 · Retención Grandes Cuentas (C2) | B5: =PARAMETROS!$B$5 -> 9 | C5: =PARAMETROS!$B$11 -> 0.3 | D5: =B5*C5 -> 2.7 | E5: =PARAMETROS!$B$17 -> 70640 | F5: =D5*E5 -> 190728 | G5: =E5 -> 70640 | H5: =D5*G5 -> 190728
A6: P3 · Captación Madrid | B6: =PARAMETROS!$B$6 -> 127 | C6: =PARAMETROS!$B$12 -> 0.08 | D6: =B6*C6 -> 10.16 | E6: =PARAMETROS!$B$18 -> 16380 | F6: =D6*E6 -> 166420.8 | G6: =E6*(1+PARAMETROS!$B$22) -> 17690.4 | H6: =D6*G6 -> 179734.46
A7: P4 · Conversión Italia | B7: =PARAMETROS!$B$7 -> 271 | C7: =PARAMETROS!$B$13 -> 0.04 | D7: =B7*C7 -> 10.84 | E7: =PARAMETROS!$B$19 -> 13672 | F7: =D7*E7 -> 148204.48 | G7: =E7*(1+PARAMETROS!$B$22) -> 14765.76 | H7: =D7*G7 -> 160060.84
A8: TOTAL ingresos incrementales | F8: =SUM(F4:F7) -> 588891.28 | H8: =SUM(H4:H7) -> 614061.3
A11: ROI INDIVIDUAL DE LA PALANCA P1
A12: Ingreso anual P1 | B12: =F4 -> 83538
A13: Coste asignado a P1 | B13: =PARAMETROS!$B$47 -> 107000
A14: Beneficio neto P1 | B14: =B12-B13 -> -23462
A15: ROI individual P1 | B15: =B14/B13 -> -0.21927103 | C15: Negativo en aislado: ver NOTAS (valor multianual)

Sheet ESCENARIOS
A1: ESCENARIOS Y ROI FINAL
A3: Escenario | B3: Ingresos 2026 | C3: ∆ vs DN | D3: Coste plan | E3: Beneficio | F3: ROI
A4: DO NOTHING | B4: =PARAMETROS!$B$44 -> 37250000 | C4: - | D4: 0 | E4: - | F4: -
A5: DO SOMETHING · Opción 1 (volumen) | B5: =PARAMETROS!$B$44+PALANCAS!$F$8 -> 37838891 | C5: =PALANCAS!$F$8 -> 588891.28 | D5: =PARAMETROS!$B$39 -> 482000 | E5: =PALANCAS!$F$8-PARAMETROS!$B$39 -> 106891.28 | F5: =(PALANCAS!$F$8-PARAMETROS!$B$39)/PARAMETROS!$B$39 -> 0.22176614
A6: DO SOMETHING · Opción 2 (volumen + ticket) | B6: =PARAMETROS!$B$44+PALANCAS!$H$8 -> 37864061 | C6: =PALANCAS!$H$8 -> 614061.3 | D6: =PARAMETROS!$B$39 -> 482000 | E6: =PALANCAS!$H$8-PARAMETROS!$B$39 -> 132061.3 | F6: =(PALANCAS!$H$8-PARAMETROS!$B$39)/PARAMETROS!$B$39 -> 0.2739861
A8: Lectura: el ROI se mide sobre el INCREMENTO respecto a DO NOTHING, no sobre la facturación total.

Sheet SENSIBILIDAD
A1: ANÁLISIS DE SENSIBILIDAD
A3: 1) Sensibilidad univariante de las TASAS DE ÉXITO (ROI Opción 1)
A4: Parámetro | B4: Pesimista | C4: ROI | D4: Base | E4: ROI | F4: Optimista | G4: ROI
A5: Tasa P1 (Retención C1) | B5: 0.15 | C5: =((PARAMETROS!$B$4*$B$5*PARAMETROS!$B$16+PARAMETROS!$B$5*PARAMETROS!$B$11*PARAMETROS!$B$17+PARAMETROS!$B$6*PARAMETROS!$B$12*PARAMETROS!$B$18+PARAMETROS!$B$7*PARAMETROS!$B$13*PARAMETROS!$B$19)-PARAMETROS!$B$39)/PARAMETROS!$B$39 -> 0.13510846 | D5: =PARAMETROS!$B$10 -> 0.3 | E5: =((PARAMETROS!$B$4*$D$5*PARAMETROS!$B$16+PARAMETROS!$B$5*PARAMETROS!$B$11*PARAMETROS!$B$17+PARAMETROS!$B$6*PARAMETROS!$B$12*PARAMETROS!$B$18+PARAMETROS!$B$7*PARAMETROS!$B$13*PARAMETROS!$B$19)-PARAMETROS!$B$39)/PARAMETROS!$B$39 -> 0.22176614 | F5: 0.45 | G5: =((PARAMETROS!$B$4*$F$5*PARAMETROS!$B$16+PARAMETROS!$B$5*PARAMETROS!$B$11*PARAMETROS!$B$17+PARAMETROS!$B$6*PARAMETROS!$B$12*PARAMETROS!$B$18+PARAMETROS!$B$7*PARAMETROS!$B$13*PARAMETROS!$B$19)-PARAMETROS!$B$39)/PARAMETROS!$B$39 -> 0.30842382
A6: Tasa P2 (Retención C2) | B6: 0.15 | C6: =((PARAMETROS!$B$4*PARAMETROS!$B$10*PARAMETROS!$B$16+PARAMETROS!$B$5*$B$6*PARAMETROS!$B$17+PARAMETROS!$B$6*PARAMETROS!$B$12*PARAMETROS!$B$18+PARAMETROS!$B$7*PARAMETROS!$B$13*PARAMETROS!$B$19)-PARAMETROS!$B$39)/PARAMETROS!$B$39 -> 0.023915519 | D6: =PARAMETROS!$B$11 -> 0.3 | E6: =((PARAMETROS!$B$4*PARAMETROS!$B$10*PARAMETROS!$B$16+PARAMETROS!$B$5*$D$6*PARAMETROS!$B$17+PARAMETROS!$B$6*PARAMETROS!$B$12*PARAMETROS!$B$18+PARAMETROS!$B$7*PARAMETROS!$B$13*PARAMETROS!$B$19)-PARAMETROS!$B$39)/PARAMETROS!$B$39 -> 0.22176614 | F6: 0.45 | G6: =((PARAMETROS!$B$4*PARAMETROS!$B$10*PARAMETROS!$B$16+PARAMETROS!$B$5*$F$6*PARAMETROS!$B$17+PARAMETROS!$B$6*PARAMETROS!$B$12*PARAMETROS!$B$18+PARAMETROS!$B$7*PARAMETROS!$B$13*PARAMETROS!$B$19)-PARAMETROS!$B$39)/PARAMETROS!$B$39 -> 0.41961676
A7: Tasa P3 (Captación Madrid) | B7: 0.04 | C7: =((PARAMETROS!$B$4*PARAMETROS!$B$10*PARAMETROS!$B$16+PARAMETROS!$B$5*PARAMETROS!$B$11*PARAMETROS!$B$17+PARAMETROS!$B$6*$B$7*PARAMETROS!$B$18+PARAMETROS!$B$7*PARAMETROS!$B$13*PARAMETROS!$B$19)-PARAMETROS!$B$39)/PARAMETROS!$B$39 -> 0.049130456 | D7: =PARAMETROS!$B$12 -> 0.08 | E7: =((PARAMETROS!$B$4*PARAMETROS!$B$10*PARAMETROS!$B$16+PARAMETROS!$B$5*PARAMETROS!$B$11*PARAMETROS!$B$17+PARAMETROS!$B$6*$D$7*PARAMETROS!$B$18+PARAMETROS!$B$7*PARAMETROS!$B$13*PARAMETROS!$B$19)-PARAMETROS!$B$39)/PARAMETROS!$B$39 -> 0.22176614 | F7: 0.15 | G7: =((PARAMETROS!$B$4*PARAMETROS!$B$10*PARAMETROS!$B$16+PARAMETROS!$B$5*PARAMETROS!$B$11*PARAMETROS!$B$17+PARAMETROS!$B$6*$F$7*PARAMETROS!$B$18+PARAMETROS!$B$7*PARAMETROS!$B$13*PARAMETROS!$B$19)-PARAMETROS!$B$39)/PARAMETROS!$B$39 -> 0.52387859
A8: Tasa P4 (Conversión Italia) | B8: 0.02 | C8: =((PARAMETROS!$B$4*PARAMETROS!$B$10*PARAMETROS!$B$16+PARAMETROS!$B$5*PARAMETROS!$B$11*PARAMETROS!$B$17+PARAMETROS!$B$6*PARAMETROS!$B$12*PARAMETROS!$B$18+PARAMETROS!$B$7*$B$8*PARAMETROS!$B$19)-PARAMETROS!$B$39)/PARAMETROS!$B$39 -> 0.068027054 | D8: =PARAMETROS!$B$13 -> 0.04 | E8: =((PARAMETROS!$B$4*PARAMETROS!$B$10*PARAMETROS!$B$16+PARAMETROS!$B$5*PARAMETROS!$B$11*PARAMETROS!$B$17+PARAMETROS!$B$6*PARAMETROS!$B$12*PARAMETROS!$B$18+PARAMETROS!$B$7*$D$8*PARAMETROS!$B$19)-PARAMETROS!$B$39)/PARAMETROS!$B$39 -> 0.22176614 | F8: 0.08 | G8: =((PARAMETROS!$B$4*PARAMETROS!$B$10*PARAMETROS!$B$16+PARAMETROS!$B$5*PARAMETROS!$B$11*PARAMETROS!$B$17+PARAMETROS!$B$6*PARAMETROS!$B$12*PARAMETROS!$B$18+PARAMETROS!$B$7*$F$8*PARAMETROS!$B$19)-PARAMETROS!$B$39)/PARAMETROS!$B$39 -> 0.52924432
A11: 2) Sensibilidad a la DEFINICIÓN DE UNIVERSO de las palancas de retención (P1, P2)
A12: Definición del universo | B12: Universo P1 | C12: Universo P2 | D12: ROI Op.1
A13: Cohorte del plan (base) — priorización por capacidad | B13: 17 | C13: 9 | D13: =(($B$13*PARAMETROS!$B$10*PARAMETROS!$B$16+$C$13*PARAMETROS!$B$11*PARAMETROS!$B$17+PARAMETROS!$B$6*PARAMETROS!$B$12*PARAMETROS!$B$18+PARAMETROS!$B$7*PARAMETROS!$B$13*PARAMETROS!$B$19)-PARAMETROS!$B$39)/PARAMETROS!$B$39 -> 0.22176614
A14: Solo membresía en el TOP-100 corregido | B14: 32 | C14: 2 | D14: =(($B$14*PARAMETROS!$B$10*PARAMETROS!$B$16+$C$14*PARAMETROS!$B$11*PARAMETROS!$B$17+PARAMETROS!$B$6*PARAMETROS!$B$12*PARAMETROS!$B$18+PARAMETROS!$B$7*PARAMETROS!$B$13*PARAMETROS!$B$19)-PARAMETROS!$B$39)/PARAMETROS!$B$39 -> 0.066923817
A15: Todos los churners esperados por cluster | B15: 49 | C15: 16 | D15: =(($B$15*PARAMETROS!$B$10*PARAMETROS!$B$16+$C$15*PARAMETROS!$B$11*PARAMETROS!$B$17+PARAMETROS!$B$6*PARAMETROS!$B$12*PARAMETROS!$B$18+PARAMETROS!$B$7*PARAMETROS!$B$13*PARAMETROS!$B$19)-PARAMETROS!$B$39)/PARAMETROS!$B$39 -> 0.85577444
A17: La cohorte base (17/9) prioriza por capacidad del equipo entre los clientes de alto valor en riesgo
A18: que identifica el modelo corregido; las otras dos filas muestran los extremos de definición.

Sheet NOTAS
A1: DEFINICIÓN DE UNIVERSOS Y TRAZABILIDAD
A3: Reconciliación con el Capítulo 7 corregido:
A4: · El modelo de churn final es Random Forest (no LightGBM), con features as-of 2024 y enfoque fresh churn.
A5: · El caso de máxima prioridad pasa a ser el cliente 16352 (Núcleo Estratégico), no el 7590.
A6: · El ranking corregido de TOP-100 contiene 32 clientes del Núcleo (C1) y 2 Grandes Cuentas (C2).
A8: Definición de los universos de retención (P1, P2):
A9: · Se definen como COHORTES DE PRIORIZACIÓN del programa (capacidad del equipo de Customer Success),
A10: no como 'número de clientes en el TOP-100'. Se eligen los clientes de mayor valor en riesgo según el
A11: modelo corregido: 17 del Núcleo y 9 Grandes Cuentas (sobre 49 y 16 churners esperados respectivamente).
A12: · La hoja SENSIBILIDAD muestra cómo cambia el ROI con otras definiciones de universo.
A14: Trazabilidad de cada palanca:
A15: · P1, P2 -> ranking de riesgo del Capítulo 7 (modelo de churn).
... A26: palancas tratadas como independientes; horizonte anual; proyección B2B inercial.

Sheet COSTE_BENEFICIO
A1: MATRIZ COSTE-BENEFICIO SOBRE EL MODELO DE CHURN (Cap. 7)
A3: PARÁMETROS DE VALORACIÓN (Cap. 7, umbral 0,35)
A4: Verdaderos positivos · TP (churner detectado) | B4: 55 | C4: matriz de confusión Cap. 7
A5: Falsos positivos · FP (falsa alarma) | B5: 50
A6: Falsos negativos · FN (churner no detectado) | B6: 31
A7: Verdaderos negativos · TN (correcto, no se actúa) | B7: 429
A8: Valor anual del cliente objetivo · V (€) | B8: 16380 | C8: ticket Núcleo (Cap. 5)
A9: Coste de intervención por cliente · c (€) | B9: 2000 | C9: retención dirigida
A10: Tasa de retención · r | B10: 0.3 | C10: benchmark Customer Success
A12: VALOR ECONÓMICO POR CELDA
A13: TP · valor unitario (r·V - c) | B13: =B10*B8-B9 -> 2914
A14: TP · valor total (TP × unitario) | B14: =B4*B13 -> 160270
A15: FP · coste total (- FP × c) | B15: =-B5*B9 -> -100000
A16: FN · coste de oportunidad (- FN × V, informativo) | B16: =-B6*B8 -> -507780
A18: RESULTADO DE LA INTERVENCIÓN DIRIGIDA
A19: Coste total de intervención ((TP+FP) × c) | B19: =(B4+B5)*B9 -> 210000
A20: Valor neto de caja (TP·(r·V-c) - FP·c) | B20: =B14+B15 -> 60270
A21: ROI de la intervención (valor neto / coste) | B21: =B20/B19 -> 0.287
A23: MATRIZ DE CONFUSIÓN (recuentos · Cap. 7, umbral 0,35)
B24: Predicho No-churn | C24: Predicho Churn
A25: Real No-churn | B25: =B7 -> 429 | C25: =B5 -> 50
A26: Real Churn | B26: =B6 -> 31 | C26: =B4 -> 55
A28: Lectura: la intervención solo es rentable si el valor del cliente (V) es alto. Por eso el plan
A29: concentra la retención en los clusters de mayor ticket (C1, C2) -> palancas P1 y P2.

Sheet SENSIBILIDAD_CRUZADA
A1: SENSIBILIDAD CRUZADA · ROI Opción 1 según tasas P3 y P4
A3: Columnas = tasa Captación Madrid (P3) · Filas = tasa Conversión Italia (P4)
A5: P4 \ P3 | B5: 0.04 | C5: 0.06 | D5: 0.08 | E5: 0.12 | F5: 0.15
A6: 0.02 | B6: =(((PARAMETROS!$B$4*PARAMETROS!$B$10*PARAMETROS!$B$16+PARAMETROS!$B$5*PARAMETROS!$B$11*PARAMETROS!$B$17)+PARAMETROS!$B$6*B$5*PARAMETROS!$B$18+PARAMETROS!$B$7*$A6*PARAMETROS!$B$19)-PARAMETROS!$B$39)/PARAMETROS!$B$39 -> -0.10460863 | C6: =(((PARAMETROS!$B$4*PARAMETROS!$B$10*PARAMETROS!$B$16+PARAMETROS!$B$5*PARAMETROS!$B$11*PARAMETROS!$B$17)+PARAMETROS!$B$6*C$5*PARAMETROS!$B$18+PARAMETROS!$B$7*$A6*PARAMETROS!$B$19)-PARAMETROS!$B$39)/PARAMETROS!$B$39 -> -0.018290788 | D6: =(((PARAMETROS!$B$4*PARAMETROS!$B$10*PARAMETROS!$B$16+PARAMETROS!$B$5*PARAMETROS!$B$11*PARAMETROS!$B$17)+PARAMETROS!$B$6*D$5*PARAMETROS!$B$18+PARAMETROS!$B$7*$A6*PARAMETROS!$B$19)-PARAMETROS!$B$39)/PARAMETROS!$B$39 -> 0.068027054 | E6: =(((PARAMETROS!$B$4*PARAMETROS!$B$10*PARAMETROS!$B$16+PARAMETROS!$B$5*PARAMETROS!$B$11*PARAMETROS!$B$17)+PARAMETROS!$B$6*E$5*PARAMETROS!$B$18+PARAMETROS!$B$7*$A6*PARAMETROS!$B$19)-PARAMETROS!$B$39)/PARAMETROS!$B$39 -> 0.24066274 | F6: =(((PARAMETROS!$B$4*PARAMETROS!$B$10*PARAMETROS!$B$16+PARAMETROS!$B$5*PARAMETROS!$B$11*PARAMETROS!$B$17)+PARAMETROS!$B$6*F$5*PARAMETROS!$B$18+PARAMETROS!$B$7*$A6*PARAMETROS!$B$19)-PARAMETROS!$B$39)/PARAMETROS!$B$39 -> 0.3701395
A7: 0.04 | B7: =(((PARAMETROS!$B$4*PARAMETROS!$B$10*PARAMETROS!$B$16+PARAMETROS!$B$5*PARAMETROS!$B$11*PARAMETROS!$B$17)+PARAMETROS!$B$6*B$5*PARAMETROS!$B$18+PARAMETROS!$B$7*$A7*PARAMETROS!$B$19)-PARAMETROS!$B$39)/PARAMETROS!$B$39 -> 0.049130456 | C7: =(((PARAMETROS!$B$4*PARAMETROS!$B$10*PARAMETROS!$B$16+PARAMETROS!$B$5*PARAMETROS!$B$11*PARAMETROS!$B$17)+PARAMETROS!$B$6*C$5*PARAMETROS!$B$18+PARAMETROS!$B$7*$A7*PARAMETROS!$B$19)-PARAMETROS!$B$39)/PARAMETROS!$B$39 -> 0.1354483 | D7: =(((PARAMETROS!$B$4*PARAMETROS!$B$10*PARAMETROS!$B$16+PARAMETROS!$B$5*PARAMETROS!$B$11*PARAMETROS!$B$17)+PARAMETROS!$B$6*D$5*PARAMETROS!$B$18+PARAMETROS!$B$7*$A7*PARAMETROS!$B$19)-PARAMETROS!$B$39)/PARAMETROS!$B$39 -> 0.22176614 | E7: =(((PARAMETROS!$B$4*PARAMETROS!$B$10*PARAMETROS!$B$16+PARAMETROS!$B$5*PARAMETROS!$B$11*PARAMETROS!$B$17)+PARAMETROS!$B$6*E$5*PARAMETROS!$B$18+PARAMETROS!$B$7*$A7*PARAMETROS!$B$19)-PARAMETROS!$B$39)/PARAMETROS!$B$39 -> 0.39440183 | F7: =(((PARAMETROS!$B$4*PARAMETROS!$B$10*PARAMETROS!$B$16+PARAMETROS!$B$5*PARAMETROS!$B$11*PARAMETROS!$B$17)+PARAMETROS!$B$6*F$5*PARAMETROS!$B$18+PARAMETROS!$B$7*$A7*PARAMETROS!$B$19)-PARAMETROS!$B$39)/PARAMETROS!$B$39 -> 0.52387859
A8: 0.06 | B8: =(((PARAMETROS!$B$4*PARAMETROS!$B$10*PARAMETROS!$B$16+PARAMETROS!$B$5*PARAMETROS!$B$11*PARAMETROS!$B$17)+PARAMETROS!$B$6*B$5*PARAMETROS!$B$18+PARAMETROS!$B$7*$A8*PARAMETROS!$B$19)-PARAMETROS!$B$39)/PARAMETROS!$B$39 -> 0.20286954 | C8: =(((PARAMETROS!$B$4*PARAMETROS!$B$10*PARAMETROS!$B$16+PARAMETROS!$B$5*PARAMETROS!$B$11*PARAMETROS!$B$17)+PARAMETROS!$B$6*C$5*PARAMETROS!$B$18+PARAMETROS!$B$7*$A8*PARAMETROS!$B$19)-PARAMETROS!$B$39)/PARAMETROS!$B$39 -> 0.28918739 | D8: =(((PARAMETROS!$B$4*PARAMETROS!$B$10*PARAMETROS!$B$16+PARAMETROS!$B$5*PARAMETROS!$B$11*PARAMETROS!$B$17)+PARAMETROS!$B$6*D$5*PARAMETROS!$B$18+PARAMETROS!$B$7*$A8*PARAMETROS!$B$19)-PARAMETROS!$B$39)/PARAMETROS!$B$39 -> 0.37550523 | E8: =(((PARAMETROS!$B$4*PARAMETROS!$B$10*PARAMETROS!$B$16+PARAMETROS!$B$5*PARAMETROS!$B$11*PARAMETROS!$B$17)+PARAMETROS!$B$6*E$5*PARAMETROS!$B$18+PARAMETROS!$B$7*$A8*PARAMETROS!$B$19)-PARAMETROS!$B$39)/PARAMETROS!$B$39 -> 0.54814091 | F8: =(((PARAMETROS!$B$4*PARAMETROS!$B$10*PARAMETROS!$B$16+PARAMETROS!$B$5*PARAMETROS!$B$11*PARAMETROS!$B$17)+PARAMETROS!$B$6*F$5*PARAMETROS!$B$18+PARAMETROS!$B$7*$A8*PARAMETROS!$B$19)-PARAMETROS!$B$39)/PARAMETROS!$B$39 -> 0.67761768
A9: 0.08 | B9: =(((PARAMETROS!$B$4*PARAMETROS!$B$10*PARAMETROS!$B$16+PARAMETROS!$B$5*PARAMETROS!$B$11*PARAMETROS!$B$17)+PARAMETROS!$B$6*B$5*PARAMETROS!$B$18+PARAMETROS!$B$7*$A9*PARAMETROS!$B$19)-PARAMETROS!$B$39)/PARAMETROS!$B$39 -> 0.35660863 | C9: =(((PARAMETROS!$B$4*PARAMETROS!$B$10*PARAMETROS!$B$16+PARAMETROS!$B$5*PARAMETROS!$B$11*PARAMETROS!$B$17)+PARAMETROS!$B$6*C$5*PARAMETROS!$B$18+PARAMETROS!$B$7*$A9*PARAMETROS!$B$19)-PARAMETROS!$B$39)/PARAMETROS!$B$39 -> 0.44292647 | D9: =(((PARAMETROS!$B$4*PARAMETROS!$B$10*PARAMETROS!$B$16+PARAMETROS!$B$5*PARAMETROS!$B$11*PARAMETROS!$B$17)+PARAMETROS!$B$6*D$5*PARAMETROS!$B$18+PARAMETROS!$B$7*$A9*PARAMETROS!$B$19)-PARAMETROS!$B$39)/PARAMETROS!$B$39 -> 0.52924432 | E9: =(((PARAMETROS!$B$4*PARAMETROS!$B$10*PARAMETROS!$B$16+PARAMETROS!$B$5*PARAMETROS!$B$11*PARAMETROS!$B$17)+PARAMETROS!$B$6*E$5*PARAMETROS!$B$18+PARAMETROS!$B$7*$A9*PARAMETROS!$B$19)-PARAMETROS!$B$39)/PARAMETROS!$B$39 -> 0.70188 | F9: =(((PARAMETROS!$B$4*PARAMETROS!$B$10*PARAMETROS!$B$16+PARAMETROS!$B$5*PARAMETROS!$B$11*PARAMETROS!$B$17)+PARAMETROS!$B$6*F$5*PARAMETROS!$B$18+PARAMETROS!$B$7*$A9*PARAMETROS!$B$19)-PARAMETROS!$B$39)/PARAMETROS!$B$39 -> 0.83135676
A12: Verde = ROI alto · Rojo = ROI bajo. La banda defendible 15-25 % queda en el centro del mapa.
A13: El caso base del plan (P3=8 %, P4=4 %) da 22,2 %.
